vapor/__init__.py
vapor/__main__.py
vapor/api_interface.py
vapor/argument_handler.py
vapor/cache_handler.py
vapor/config_handler.py
vapor/data_structures.py
vapor/exceptions.py
vapor/main.py
vapor/main.tcss
vapor_steam-1.7.0.dist-info/METADATA
vapor_steam-1.7.0.dist-info/WHEEL
vapor_steam-1.7.0.dist-info/entry_points.txt
vapor_steam-1.7.0.dist-info/licenses/LICENSE
vapor_steam-1.7.0.dist-info/RECORD
