Metadata-Version: 2.4
Name: vapor-steam
Version: 1.7.0
Summary: TUI program to check the ProtonDB compatibility of all the games of a Steam user.
License: GPLv3
License-File: LICENSE
Keywords: steam,protondb,compatibility,textual,tui
Author: TabulateJarl8
Author-email: tabulatejarl8@gmail.com
Requires-Python: >=3.9.0,<4.0.0
Classifier: Development Status :: 5 - Production/Stable
Classifier: Environment :: Console
Classifier: Intended Audience :: End Users/Desktop
Classifier: License :: OSI Approved :: GNU General Public License v3 (GPLv3)
Classifier: License :: Other/Proprietary License
Classifier: Natural Language :: English
Classifier: Operating System :: OS Independent
Classifier: Programming Language :: Python :: 3
Classifier: Programming Language :: Python :: 3.9
Classifier: Programming Language :: Python :: 3.10
Classifier: Programming Language :: Python :: 3.11
Classifier: Programming Language :: Python :: 3.12
Classifier: Programming Language :: Python :: 3.13
Classifier: Programming Language :: Python :: 3.14
Classifier: Typing :: Typed
Requires-Dist: aiohttp (>=3.13.3,<4.0.0)
Requires-Dist: platformdirs (>=4.4.0,<4.5.0) ; python_version < "3.10"
Requires-Dist: platformdirs (>=4.5.0,<5.0.0) ; python_version >= "3.10"
Requires-Dist: textual (>=7.2.0,<8.0.0)
Requires-Dist: typing-extensions (>=4.15.0,<5.0.0)
Project-URL: Homepage, https://tabulate.tech/software/vapor
Project-URL: Repository, https://github.com/TabulateJarl8/vapor
